README.md
VERSION
unagi/__init__.py
unagi/collections/__init__.py
unagi/collections/abstractlist.py
unagi/collections/greenparlazylist.py
unagi/collections/greenparlist.py
unagi/collections/lazylist.py
unagi/collections/parlist.py
unagi/fileapi/__init__.py
unagi/fileapi/fileapi.py
unagi/main.py
unagi_tools-0.1.0.dist-info/METADATA
unagi_tools-0.1.0.dist-info/WHEEL
unagi_tools-0.1.0.dist-info/RECORD
